vtils/__init__.py
vtils/cloud.py
vtils/util.py
vtils-0.1.1.dist-info/LICENSE
vtils-0.1.1.dist-info/METADATA
vtils-0.1.1.dist-info/WHEEL
vtils-0.1.1.dist-info/top_level.txt
vtils-0.1.1.dist-info/RECORD
