Metadata-Version: 2.1
Name: vtils
Version: 0.1.1
Summary: Vtils Python Library
Author: Venkateswara Rao Thota
License: MIT
License-File: LICENSE
Requires-Dist: PyCryptodome
Requires-Dist: boto3
